{
  "data": {
    "topics": [
      {
        "nodeId": 1067,
        "nodeName": "Introduction",
        "orderId": 1,
        "seqNum": 1,
        "publishedFlashcardCount": 1,
        "publishedVideoCount": 2,
        "totalPublishedFlashcardCount": null,
        "totalPublishedVideoCount": null,
        "totalFlashcardCount": 1,
        "totalVideoCount": 2,
        "totalCompletedFlashcardCount": null,
        "totalCompletedVideoCount": null,
        "levelInprogress": null,
        "completedNodes": null,
        "practiceAttempted": null,
        "practiceProgress": null,
        "totalExercises": null,
        "isCompleted": null,
        "completedDate": null,
        "subtopics": [
          {
            "nodeId": 2410,
            "nodeName": "Introduction ",
            "orderId": 1,
            "seqNum": 1,
            "description": "",
            "publishedFlashcardCount": 1,
            "publishedVideoCount": 2,
            "totalFlashcardCount": 1,
            "totalVideoCount": 2,
            "practiceProgress": null,
            "totalExercises": null,
            "isCompleted": null,
            "completedDate": null,
            "isBookmarked": null,
            "bookmarkedDate": null
          }
        ],
        "videos": null
      },
      {
        "nodeId": 1068,
        "nodeName": "Electric Charge",
        "orderId": 2,
        "seqNum": 2,
        "publishedFlashcardCount": 1,
        "publishedVideoCount": 1,
        "totalPublishedFlashcardCount": null,
        "totalPublishedVideoCount": null,
        "totalFlashcardCount": 1,
        "totalVideoCount": 2,
        "totalCompletedFlashcardCount": null,
        "totalCompletedVideoCount": null,
        "levelInprogress": null,
        "completedNodes": null,
        "practiceAttempted": null,
        "practiceProgress": null,
        "totalExercises": null,
        "isCompleted": null,
        "completedDate": null,
        "subtopics": [
          {
            "nodeId": 2411,
            "nodeName": "Electric Charge ",
            "orderId": 1,
            "seqNum": 1,
            "description": "",
            "publishedFlashcardCount": 1,
            "publishedVideoCount": 1,
            "totalFlashcardCount": 1,
            "totalVideoCount": 2,
            "practiceProgress": null,
            "totalExercises": null,
            "isCompleted": null,
            "completedDate": null,
            "isBookmarked": null,
            "bookmarkedDate": null
          }
        ],
        "videos": null
      },
      {
        "nodeId": 1069,
        "nodeName": "Conductors and Insulators",
        "orderId": 3,
        "seqNum": 3,
        "publishedFlashcardCount": 1,
        "publishedVideoCount": 1,
        "totalPublishedFlashcardCount": null,
        "totalPublishedVideoCount": null,
        "totalFlashcardCount": 1,
        "totalVideoCount": 1,
        "totalCompletedFlashcardCount": null,
        "totalCompletedVideoCount": null,
        "levelInprogress": null,
        "completedNodes": null,
        "practiceAttempted": null,
        "practiceProgress": null,
        "totalExercises": null,
        "isCompleted": null,
        "completedDate": null,
        "subtopics": [
          {
            "nodeId": 2412,
            "nodeName": "Conductors and Insulators ",
            "orderId": 1,
            "seqNum": 1,
            "description": "",
            "publishedFlashcardCount": 1,
            "publishedVideoCount": 1,
            "totalFlashcardCount": 1,
            "totalVideoCount": 1,
            "practiceProgress": null,
            "totalExercises": null,
            "isCompleted": null,
            "completedDate": null,
            "isBookmarked": null,
            "bookmarkedDate": null
          }
        ],
        "videos": null
      },
      {
        "nodeId": 1070,
        "nodeName": "Charging by Induction",
        "orderId": 4,
        "seqNum": 4,
        "publishedFlashcardCount": 3,
        "publishedVideoCount": 1,
        "totalPublishedFlashcardCount": null,
        "totalPublishedVideoCount": null,
        "totalFlashcardCount": 3,
        "totalVideoCount": 1,
        "totalCompletedFlashcardCount": null,
        "totalCompletedVideoCount": null,
        "levelInprogress": null,
        "completedNodes": null,
        "practiceAttempted": null,
        "practiceProgress": null,
        "totalExercises": null,
        "isCompleted": null,
        "completedDate": null,
        "subtopics": [
          {
            "nodeId": 2413,
            "nodeName": "Charging by Induction ",
            "orderId": 1,
            "seqNum": 1,
            "description": "",
            "publishedFlashcardCount": 1,
            "publishedVideoCount": 1,
            "totalFlashcardCount": 1,
            "totalVideoCount": 1,
            "practiceProgress": null,
            "totalExercises": null,
            "isCompleted": null,
            "completedDate": null,
            "isBookmarked": null,
            "bookmarkedDate": null
          },
          {
            "nodeId": 2414,
            "nodeName": "Charging by conduction ",
            "orderId": 2,
            "seqNum": 2,
            "description": "",
            "publishedFlashcardCount": 1,
            "publishedVideoCount": 0,
            "totalFlashcardCount": 1,
            "totalVideoCount": 0,
            "practiceProgress": null,
            "totalExercises": null,
            "isCompleted": null,
            "completedDate": null,
            "isBookmarked": null,
            "bookmarkedDate": null
          },
          {
            "nodeId": 2415,
            "nodeName": "Electroscope",
            "orderId": 3,
            "seqNum": 3,
            "description": "",
            "publishedFlashcardCount": 1,
            "publishedVideoCount": 0,
            "totalFlashcardCount": 1,
            "totalVideoCount": 0,
            "practiceProgress": null,
            "totalExercises": null,
            "isCompleted": null,
            "completedDate": null,
            "isBookmarked": null,
            "bookmarkedDate": null
          }
        ],
        "videos": null
      },
      {
        "nodeId": 1071,
        "nodeName": "Basic Properties of Electric Charge",
        "orderId": 5,
        "seqNum": 5,
        "publishedFlashcardCount": 3,
        "publishedVideoCount": 3,
        "totalPublishedFlashcardCount": null,
        "totalPublishedVideoCount": null,
        "totalFlashcardCount": 3,
        "totalVideoCount": 3,
        "totalCompletedFlashcardCount": null,
        "totalCompletedVideoCount": null,
        "levelInprogress": null,
        "completedNodes": null,
        "practiceAttempted": null,
        "practiceProgress": null,
        "totalExercises": null,
        "isCompleted": null,
        "completedDate": null,
        "subtopics": [
          {
            "nodeId": 2416,
            "nodeName": "Additivity of charges",
            "orderId": 1,
            "seqNum": 1,
            "description": null,
            "publishedFlashcardCount": 1,
            "publishedVideoCount": 1,
            "totalFlashcardCount": 1,
            "totalVideoCount": 1,
            "practiceProgress": null,
            "totalExercises": null,
            "isCompleted": null,
            "completedDate": null,
            "isBookmarked": null,
            "bookmarkedDate": null
          },
          {
            "nodeId": 2417,
            "nodeName": "Charge is conserved",
            "orderId": 2,
            "seqNum": 2,
            "description": "",
            "publishedFlashcardCount": 1,
            "publishedVideoCount": 1,
            "totalFlashcardCount": 1,
            "totalVideoCount": 1,
            "practiceProgress": null,
            "totalExercises": null,
            "isCompleted": null,
            "completedDate": null,
            "isBookmarked": null,
            "bookmarkedDate": null
          },
          {
            "nodeId": 2418,
            "nodeName": "Quantisation of charge",
            "orderId": 3,
            "seqNum": 3,
            "description": "",
            "publishedFlashcardCount": 1,
            "publishedVideoCount": 1,
            "totalFlashcardCount": 1,
            "totalVideoCount": 1,
            "practiceProgress": null,
            "totalExercises": null,
            "isCompleted": null,
            "completedDate": null,
            "isBookmarked": null,
            "bookmarkedDate": null
          }
        ],
        "videos": null
      },
      {
        "nodeId": 1072,
        "nodeName": "Coulomb’s Law",
        "orderId": 6,
        "seqNum": 6,
        "publishedFlashcardCount": 6,
        "publishedVideoCount": 3,
        "totalPublishedFlashcardCount": null,
        "totalPublishedVideoCount": null,
        "totalFlashcardCount": 6,
        "totalVideoCount": 3,
        "totalCompletedFlashcardCount": null,
        "totalCompletedVideoCount": null,
        "levelInprogress": null,
        "completedNodes": null,
        "practiceAttempted": null,
        "practiceProgress": null,
        "totalExercises": null,
        "isCompleted": null,
        "completedDate": null,
        "subtopics": [
          {
            "nodeId": 2419,
            "nodeName": "Coulombs law in Vector form",
            "orderId": 1,
            "seqNum": 1,
            "description": "",
            "publishedFlashcardCount": 1,
            "publishedVideoCount": 1,
            "totalFlashcardCount": 1,
            "totalVideoCount": 1,
            "practiceProgress": null,
            "totalExercises": null,
            "isCompleted": null,
            "completedDate": null,
            "isBookmarked": null,
            "bookmarkedDate": null
          },
          {
            "nodeId": 2420,
            "nodeName": "Permittivity and relative permittivity",
            "orderId": 2,
            "seqNum": 2,
            "description": "",
            "publishedFlashcardCount": 1,
            "publishedVideoCount": 1,
            "totalFlashcardCount": 1,
            "totalVideoCount": 1,
            "practiceProgress": null,
            "totalExercises": null,
            "isCompleted": null,
            "completedDate": null,
            "isBookmarked": null,
            "bookmarkedDate": null
          },
          {
            "nodeId": 2421,
            "nodeName": "Principle of superposition of electric forces (Forces between Multiple Charges)",
            "orderId": 3,
            "seqNum": 3,
            "description": null,
            "publishedFlashcardCount": 2,
            "publishedVideoCount": 1,
            "totalFlashcardCount": 2,
            "totalVideoCount": 1,
            "practiceProgress": null,
            "totalExercises": null,
            "isCompleted": null,
            "completedDate": null,
            "isBookmarked": null,
            "bookmarkedDate": null
          },
          {
            "nodeId": 2422,
            "nodeName": "Force due to continuous charge distribution",
            "orderId": 4,
            "seqNum": 4,
            "description": "",
            "publishedFlashcardCount": 1,
            "publishedVideoCount": 0,
            "totalFlashcardCount": 1,
            "totalVideoCount": 0,
            "practiceProgress": null,
            "totalExercises": null,
            "isCompleted": null,
            "completedDate": null,
            "isBookmarked": null,
            "bookmarkedDate": null
          },
          {
            "nodeId": 2423,
            "nodeName": "Equilibrium of System of Charges",
            "orderId": 5,
            "seqNum": 5,
            "description": null,
            "publishedFlashcardCount": 1,
            "publishedVideoCount": 0,
            "totalFlashcardCount": 1,
            "totalVideoCount": 0,
            "practiceProgress": null,
            "totalExercises": null,
            "isCompleted": null,
            "completedDate": null,
            "isBookmarked": null,
            "bookmarkedDate": null
          }
        ],
        "videos": null
      },
      {
        "nodeId": 1074,
        "nodeName": "Electric Field",
        "orderId": 8,
        "seqNum": 7,
        "publishedFlashcardCount": 7,
        "publishedVideoCount": 5,
        "totalPublishedFlashcardCount": null,
        "totalPublishedVideoCount": null,
        "totalFlashcardCount": 7,
        "totalVideoCount": 5,
        "totalCompletedFlashcardCount": null,
        "totalCompletedVideoCount": null,
        "levelInprogress": null,
        "completedNodes": null,
        "practiceAttempted": null,
        "practiceProgress": null,
        "totalExercises": null,
        "isCompleted": null,
        "completedDate": null,
        "subtopics": [
          {
            "nodeId": 2425,
            "nodeName": "Electric field due to a point charge",
            "orderId": 1,
            "seqNum": 1,
            "description": "",
            "publishedFlashcardCount": 1,
            "publishedVideoCount": 1,
            "totalFlashcardCount": 1,
            "totalVideoCount": 1,
            "practiceProgress": null,
            "totalExercises": null,
            "isCompleted": null,
            "completedDate": null,
            "isBookmarked": null,
            "bookmarkedDate": null
          },
          {
            "nodeId": 2426,
            "nodeName": "Electric field due to a system of charges",
            "orderId": 2,
            "seqNum": 2,
            "description": "",
            "publishedFlashcardCount": 1,
            "publishedVideoCount": 1,
            "totalFlashcardCount": 1,
            "totalVideoCount": 1,
            "practiceProgress": null,
            "totalExercises": null,
            "isCompleted": null,
            "completedDate": null,
            "isBookmarked": null,
            "bookmarkedDate": null
          },
          {
            "nodeId": 2427,
            "nodeName": "Relation between force and field",
            "orderId": 3,
            "seqNum": 3,
            "description": "",
            "publishedFlashcardCount": 1,
            "publishedVideoCount": 1,
            "totalFlashcardCount": 1,
            "totalVideoCount": 1,
            "practiceProgress": null,
            "totalExercises": null,
            "isCompleted": null,
            "completedDate": null,
            "isBookmarked": null,
            "bookmarkedDate": null
          },
          {
            "nodeId": 2428,
            "nodeName": "Physical significance of electric field",
            "orderId": 4,
            "seqNum": 4,
            "description": "",
            "publishedFlashcardCount": 1,
            "publishedVideoCount": 1,
            "totalFlashcardCount": 1,
            "totalVideoCount": 1,
            "practiceProgress": null,
            "totalExercises": null,
            "isCompleted": null,
            "completedDate": null,
            "isBookmarked": null,
            "bookmarkedDate": null
          },
          {
            "nodeId": 2429,
            "nodeName": "Motion of Charged particle in a electric field",
            "orderId": 5,
            "seqNum": 5,
            "description": "",
            "publishedFlashcardCount": 1,
            "publishedVideoCount": 0,
            "totalFlashcardCount": 1,
            "totalVideoCount": 0,
            "practiceProgress": null,
            "totalExercises": null,
            "isCompleted": null,
            "completedDate": null,
            "isBookmarked": null,
            "bookmarkedDate": null
          },
          {
            "nodeId": 2430,
            "nodeName": "Principle of superposition of electric field",
            "orderId": 6,
            "seqNum": 6,
            "description": "",
            "publishedFlashcardCount": 1,
            "publishedVideoCount": 0,
            "totalFlashcardCount": 1,
            "totalVideoCount": 0,
            "practiceProgress": null,
            "totalExercises": null,
            "isCompleted": null,
            "completedDate": null,
            "isBookmarked": null,
            "bookmarkedDate": null
          },
          {
            "nodeId": 2431,
            "nodeName": "Electric field due to continuous charge distribution",
            "orderId": 7,
            "seqNum": 7,
            "description": "",
            "publishedFlashcardCount": 1,
            "publishedVideoCount": 1,
            "totalFlashcardCount": 1,
            "totalVideoCount": 1,
            "practiceProgress": null,
            "totalExercises": null,
            "isCompleted": null,
            "completedDate": null,
            "isBookmarked": null,
            "bookmarkedDate": null
          }
        ],
        "videos": null
      },
      {
        "nodeId": 1075,
        "nodeName": "Electric Field Lines",
        "orderId": 9,
        "seqNum": 8,
        "publishedFlashcardCount": 1,
        "publishedVideoCount": 1,
        "totalPublishedFlashcardCount": null,
        "totalPublishedVideoCount": null,
        "totalFlashcardCount": 1,
        "totalVideoCount": 1,
        "totalCompletedFlashcardCount": null,
        "totalCompletedVideoCount": null,
        "levelInprogress": null,
        "completedNodes": null,
        "practiceAttempted": null,
        "practiceProgress": null,
        "totalExercises": null,
        "isCompleted": null,
        "completedDate": null,
        "subtopics": [
          {
            "nodeId": 2432,
            "nodeName": "Electric Field Lines ",
            "orderId": 1,
            "seqNum": 1,
            "description": "",
            "publishedFlashcardCount": 1,
            "publishedVideoCount": 1,
            "totalFlashcardCount": 1,
            "totalVideoCount": 1,
            "practiceProgress": null,
            "totalExercises": null,
            "isCompleted": null,
            "completedDate": null,
            "isBookmarked": null,
            "bookmarkedDate": null
          }
        ],
        "videos": null
      },
      {
        "nodeId": 1076,
        "nodeName": "Electric Flux",
        "orderId": 10,
        "seqNum": 9,
        "publishedFlashcardCount": 1,
        "publishedVideoCount": 2,
        "totalPublishedFlashcardCount": null,
        "totalPublishedVideoCount": null,
        "totalFlashcardCount": 1,
        "totalVideoCount": 2,
        "totalCompletedFlashcardCount": null,
        "totalCompletedVideoCount": null,
        "levelInprogress": null,
        "completedNodes": null,
        "practiceAttempted": null,
        "practiceProgress": null,
        "totalExercises": null,
        "isCompleted": null,
        "completedDate": null,
        "subtopics": [
          {
            "nodeId": 2433,
            "nodeName": "Calculation of Electric Flux",
            "orderId": 1,
            "seqNum": 1,
            "description": "",
            "publishedFlashcardCount": 1,
            "publishedVideoCount": 2,
            "totalFlashcardCount": 1,
            "totalVideoCount": 2,
            "practiceProgress": null,
            "totalExercises": null,
            "isCompleted": null,
            "completedDate": null,
            "isBookmarked": null,
            "bookmarkedDate": null
          }
        ],
        "videos": null
      },
      {
        "nodeId": 1077,
        "nodeName": "Electric Dipole",
        "orderId": 11,
        "seqNum": 10,
        "publishedFlashcardCount": 4,
        "publishedVideoCount": 3,
        "totalPublishedFlashcardCount": null,
        "totalPublishedVideoCount": null,
        "totalFlashcardCount": 4,
        "totalVideoCount": 3,
        "totalCompletedFlashcardCount": null,
        "totalCompletedVideoCount": null,
        "levelInprogress": null,
        "completedNodes": null,
        "practiceAttempted": null,
        "practiceProgress": null,
        "totalExercises": null,
        "isCompleted": null,
        "completedDate": null,
        "subtopics": [
          {
            "nodeId": 2434,
            "nodeName": "The field of an electric dipole",
            "orderId": 1,
            "seqNum": 1,
            "description": "",
            "publishedFlashcardCount": 2,
            "publishedVideoCount": 3,
            "totalFlashcardCount": 2,
            "totalVideoCount": 3,
            "practiceProgress": null,
            "totalExercises": null,
            "isCompleted": null,
            "completedDate": null,
            "isBookmarked": null,
            "bookmarkedDate": null
          },
          {
            "nodeId": 2435,
            "nodeName": "Force between two dipoles",
            "orderId": 2,
            "seqNum": 2,
            "description": null,
            "publishedFlashcardCount": 1,
            "publishedVideoCount": 0,
            "totalFlashcardCount": 1,
            "totalVideoCount": 0,
            "practiceProgress": null,
            "totalExercises": null,
            "isCompleted": null,
            "completedDate": null,
            "isBookmarked": null,
            "bookmarkedDate": null
          },
          {
            "nodeId": 2436,
            "nodeName": "Physical significance of dipoles",
            "orderId": 3,
            "seqNum": 3,
            "description": "",
            "publishedFlashcardCount": 1,
            "publishedVideoCount": 0,
            "totalFlashcardCount": 1,
            "totalVideoCount": 0,
            "practiceProgress": null,
            "totalExercises": null,
            "isCompleted": null,
            "completedDate": null,
            "isBookmarked": null,
            "bookmarkedDate": null
          }
        ],
        "videos": null
      },
      {
        "nodeId": 1078,
        "nodeName": "Dipole in an External Field",
        "orderId": 12,
        "seqNum": 11,
        "publishedFlashcardCount": 1,
        "publishedVideoCount": 4,
        "totalPublishedFlashcardCount": null,
        "totalPublishedVideoCount": null,
        "totalFlashcardCount": 1,
        "totalVideoCount": 4,
        "totalCompletedFlashcardCount": null,
        "totalCompletedVideoCount": null,
        "levelInprogress": null,
        "completedNodes": null,
        "practiceAttempted": null,
        "practiceProgress": null,
        "totalExercises": null,
        "isCompleted": null,
        "completedDate": null,
        "subtopics": [
          {
            "nodeId": 2437,
            "nodeName": "Force and Torque on Dipole",
            "orderId": 1,
            "seqNum": 1,
            "description": null,
            "publishedFlashcardCount": 1,
            "publishedVideoCount": 4,
            "totalFlashcardCount": 1,
            "totalVideoCount": 4,
            "practiceProgress": null,
            "totalExercises": null,
            "isCompleted": null,
            "completedDate": null,
            "isBookmarked": null,
            "bookmarkedDate": null
          }
        ],
        "videos": null
      },
      {
        "nodeId": 1079,
        "nodeName": "Continuous Charge Distribution",
        "orderId": 13,
        "seqNum": 12,
        "publishedFlashcardCount": 1,
        "publishedVideoCount": 0,
        "totalPublishedFlashcardCount": null,
        "totalPublishedVideoCount": null,
        "totalFlashcardCount": 1,
        "totalVideoCount": 0,
        "totalCompletedFlashcardCount": null,
        "totalCompletedVideoCount": null,
        "levelInprogress": null,
        "completedNodes": null,
        "practiceAttempted": null,
        "practiceProgress": null,
        "totalExercises": null,
        "isCompleted": null,
        "completedDate": null,
        "subtopics": [
          {
            "nodeId": 7458,
            "nodeName": "Continuous Charge Distribution",
            "orderId": 2,
            "seqNum": 1,
            "description": null,
            "publishedFlashcardCount": 1,
            "publishedVideoCount": 0,
            "totalFlashcardCount": 1,
            "totalVideoCount": 0,
            "practiceProgress": null,
            "totalExercises": null,
            "isCompleted": null,
            "completedDate": null,
            "isBookmarked": null,
            "bookmarkedDate": null
          }
        ],
        "videos": null
      },
      {
        "nodeId": 1080,
        "nodeName": "Gauss’s Law",
        "orderId": 14,
        "seqNum": 13,
        "publishedFlashcardCount": 1,
        "publishedVideoCount": 2,
        "totalPublishedFlashcardCount": null,
        "totalPublishedVideoCount": null,
        "totalFlashcardCount": 1,
        "totalVideoCount": 2,
        "totalCompletedFlashcardCount": null,
        "totalCompletedVideoCount": null,
        "levelInprogress": null,
        "completedNodes": null,
        "practiceAttempted": null,
        "practiceProgress": null,
        "totalExercises": null,
        "isCompleted": null,
        "completedDate": null,
        "subtopics": [
          {
            "nodeId": 2440,
            "nodeName": "Gauss’s Law ",
            "orderId": 1,
            "seqNum": 1,
            "description": "",
            "publishedFlashcardCount": 1,
            "publishedVideoCount": 2,
            "totalFlashcardCount": 1,
            "totalVideoCount": 2,
            "practiceProgress": null,
            "totalExercises": null,
            "isCompleted": null,
            "completedDate": null,
            "isBookmarked": null,
            "bookmarkedDate": null
          }
        ],
        "videos": null
      },
      {
        "nodeId": 1081,
        "nodeName": "Applications of Gauss’s Law",
        "orderId": 15,
        "seqNum": 14,
        "publishedFlashcardCount": 5,
        "publishedVideoCount": 8,
        "totalPublishedFlashcardCount": null,
        "totalPublishedVideoCount": null,
        "totalFlashcardCount": 5,
        "totalVideoCount": 8,
        "totalCompletedFlashcardCount": null,
        "totalCompletedVideoCount": null,
        "levelInprogress": null,
        "completedNodes": null,
        "practiceAttempted": null,
        "practiceProgress": null,
        "totalExercises": null,
        "isCompleted": null,
        "completedDate": null,
        "subtopics": [
          {
            "nodeId": 2441,
            "nodeName": "Field due to an infinitely long straight uniformly charged wire",
            "orderId": 1,
            "seqNum": 1,
            "description": "",
            "publishedFlashcardCount": 1,
            "publishedVideoCount": 2,
            "totalFlashcardCount": 1,
            "totalVideoCount": 2,
            "practiceProgress": null,
            "totalExercises": null,
            "isCompleted": null,
            "completedDate": null,
            "isBookmarked": null,
            "bookmarkedDate": null
          },
          {
            "nodeId": 2442,
            "nodeName": "Field due to a uniformly charged infinite plane sheet",
            "orderId": 2,
            "seqNum": 2,
            "description": "",
            "publishedFlashcardCount": 1,
            "publishedVideoCount": 2,
            "totalFlashcardCount": 1,
            "totalVideoCount": 2,
            "practiceProgress": null,
            "totalExercises": null,
            "isCompleted": null,
            "completedDate": null,
            "isBookmarked": null,
            "bookmarkedDate": null
          },
          {
            "nodeId": 2443,
            "nodeName": "Field due to a uniformly charged thin spherical shell/conducting solid sphere",
            "orderId": 3,
            "seqNum": 3,
            "description": "",
            "publishedFlashcardCount": 1,
            "publishedVideoCount": 2,
            "totalFlashcardCount": 1,
            "totalVideoCount": 2,
            "practiceProgress": null,
            "totalExercises": null,
            "isCompleted": null,
            "completedDate": null,
            "isBookmarked": null,
            "bookmarkedDate": null
          },
          {
            "nodeId": 2444,
            "nodeName": "Field due to a uniformly charged non conducting solid sphere",
            "orderId": 4,
            "seqNum": 4,
            "description": "",
            "publishedFlashcardCount": 1,
            "publishedVideoCount": 2,
            "totalFlashcardCount": 1,
            "totalVideoCount": 2,
            "practiceProgress": null,
            "totalExercises": null,
            "isCompleted": null,
            "completedDate": null,
            "isBookmarked": null,
            "bookmarkedDate": null
          },
          {
            "nodeId": 7250,
            "nodeName": "Field due to Uniformly charged Cylinder",
            "orderId": 5,
            "seqNum": 5,
            "description": null,
            "publishedFlashcardCount": 1,
            "publishedVideoCount": 0,
            "totalFlashcardCount": 1,
            "totalVideoCount": 0,
            "practiceProgress": null,
            "totalExercises": null,
            "isCompleted": null,
            "completedDate": null,
            "isBookmarked": null,
            "bookmarkedDate": null
          }
        ],
        "videos": null
      }
    ]
  },
  "message": "Success",
  "status": true
}